{
  "name": "Starting an Open Source Project",
  "slug": "starting-an-open-source-project",
  "keepStatus": "keepCandidate",
  "description": "Launching a successful open source project involves more than just code. Start your journey here.",
  "url": "https://opensource.guide/starting-a-project/",
  "author": "GitHub",
  "license": "CC-BY-4.0",
  "learnerCategory": "Maintaining & Sustaining Software",
  "educationalLevel": "Beginner",
  "ossRole": "Contributor, Maintainer",
  "subTopic": "",
  "timeRequired": "",
  "learningResourceType": "Guide",
  "inLanguage": [
    "English, Chinese (Traditional)/繁體中文, Chinese (Simplified) / 简体中文, French/Français, Turkish/Türkçe, Persian/Farsi, Tamil/தமிழ், Spanish/Español, Swahili, Hindi, Russian/Русский, Hungarian/Magyar, Romanian, Bengali/Bangla, Portuguese, Bulgarian/Български, Polish, Nigerian Pidgin, German/Deutsch, Dutch, Greek/Ελληνικά, Malay, Japanese/日本語, Korean/한국어, Italian, Indonesian"
  ],
  "keywords": [
    "starting",
    "open source",
    "launch"
  ],
  "topic": "Maintaining",
  "sortingId": "18",
  "dependsOn": "13 - Introduction to Git | 33 - Understanding Software Licensing",
  "learningObjectives": "",
  "ospoRelevance": "Core",
  "about": "",
  "abstract": "Learn the foundational steps for launching a successful open source project, from defining its purpose and choosing a license to setting up version control and creating a contributor-friendly environment.",
  "accessibilitySummary": "",
  "audience": "Developers, Communities",
  "competencyRequired": "",
  "contributor": "",
  "creativeWorkStatus": "",
  "dateCreated": "",
  "dateModified": "",
  "datePublished": "",
  "hasPart": "",
  "identifier": "",
  "isPartOf": "Open Source Guides",
  "notes": "",
  "mentions": "These guides are available in over 20 languages.",
  "recordedAt": "",
  "teaches": "",
  "version": "",
  "workTranslation": ""
}
